README.rst
setup.py
src/appstart/__init__.py
src/appstart/core.py
src/appstart.egg-info/PKG-INFO
src/appstart.egg-info/SOURCES.txt
src/appstart.egg-info/dependency_links.txt
src/appstart.egg-info/requires.txt
src/appstart.egg-info/top_level.txt
src/scripts/appserver
src/scripts/appserver.py
test/test.py