Metadata-Version: 1.1
Name: appstart
Version: 0.3.1
Summary: Application server framework help you write long run application.
Home-page: https://github.com/appstore-zencore/appstart
Author: zencore
Author-email: dobetter@zencore.cn
License: MIT
Keywords: appstart
Platform: UNKNOWN
Classifier: Development Status :: 5 - Production/Stable
Classifier: Intended Audience :: Developers
Classifier: Topic :: Software Development :: Libraries :: Python Modules
Classifier: License :: OSI Approved :: MIT License
Classifier: Programming Language :: Python :: 3
Classifier: Programming Language :: Python :: 3 :: Only
Requires: six
Requires: click
Requires: pyyaml
Requires: daemon_application
Requires: dictop
Requires: magic_import
